database_automation/__init__.py
database_automation/mongo_crud.py
mongodatabaseautomator-0.0.5.dist-info/METADATA
mongodatabaseautomator-0.0.5.dist-info/WHEEL
mongodatabaseautomator-0.0.5.dist-info/top_level.txt
mongodatabaseautomator-0.0.5.dist-info/RECORD
